freakotp/__init__.py
freakotp/cli.py
freakotp/secret.py
freakotp/sql.py
freakotp/token.py
freakotp-3.0.7.dist-info/LICENSE
freakotp-3.0.7.dist-info/METADATA
freakotp-3.0.7.dist-info/WHEEL
freakotp-3.0.7.dist-info/entry_points.txt
freakotp-3.0.7.dist-info/top_level.txt
freakotp-3.0.7.dist-info/zip-safe
freakotp-3.0.7.dist-info/RECORD
