Metadata-Version: 2.1
Name: freakotp
Version: 3.0.7
Summary: FreakOTP is a command line two-factor authentication application
Home-page: http://github.com/andreax79/FreakOTP
Author: Andrea Bonomi
Author-email: andrea.bonomi@gmail.com
License: MIT
Project-URL: Bug Tracker, http://github.com/andreax79/FreakOTP/issues
Project-URL: Documentation, https://FreakOTP.readthedocs.io/en/latest/
Project-URL: Source Code, http://github.com/andreax79/FreakOTP
Keywords: cli,otp,two-factor,totp,hotp,freeotp
Platform: any
Classifier: Development Status :: 5 - Production/Stable
Classifier: Environment :: Console
Classifier: Intended Audience :: Developers
Classifier: License :: OSI Approved :: MIT License
Classifier: Operating System :: OS Independent
Classifier: Programming Language :: Python
Classifier: Topic :: Utilities
Classifier: Programming Language :: Python :: 3.6
Classifier: Programming Language :: Python :: 3.7
Classifier: Programming Language :: Python :: 3.8
Classifier: Programming Language :: Python :: 3.9
Classifier: Programming Language :: Python :: 3.10
Classifier: Programming Language :: Python :: 3.11
Classifier: Programming Language :: Python :: 3.12
Requires-Python: >=3.6
License-File: LICENSE
Requires-Dist: appdirs
Requires-Dist: qrcode
Requires-Dist: click
Requires-Dist: pzp >=0.0.21
Provides-Extra: test
Requires-Dist: pytest ; extra == 'test'
